odoo9_addon_event_phone-9.0.1.0.0.99.dev2-py2.7-nspkg.pth
odoo9_addon_event_phone-9.0.1.0.0.99.dev2.dist-info/METADATA
odoo9_addon_event_phone-9.0.1.0.0.99.dev2.dist-info/RECORD
odoo9_addon_event_phone-9.0.1.0.0.99.dev2.dist-info/WHEEL
odoo9_addon_event_phone-9.0.1.0.0.99.dev2.dist-info/namespace_packages.txt
odoo9_addon_event_phone-9.0.1.0.0.99.dev2.dist-info/top_level.txt
odoo_addons/event_phone/__init__.py
odoo_addons/event_phone/__openerp__.py
odoo_addons/event_phone/event_phone.py
odoo_addons/event_phone/event_view.xml
odoo_addons/event_phone/security/ir.model.access.csv
odoo_addons/event_phone/static/description/icon.png
